[
    {
        "img": "cover/JRCover.jpg",
        "title": "Wuwow Junior學員系統改版",
        "date": "2024",
        "id": "web6"
    },
    {
        "img": "cover/wuwowWebCover.jpg",
        "title": "Wuwow官網翻新",
        "date": "2023",
        "id": "web7"
    },
    {
        "img": "cover/TempleWebCover.jpg",
        "title": "鎮瀾宮官網",
        "date": "2022",
        "id": "web2"
    },
    {
        "img": "cover/iEstateWebCover.jpg",
        "title": "iEstate｜不動產P2P借貸媒合平台",
        "date": "2022",
        "id": "web1"
    },
  
    {
        "img": "cover/ProgroupWebCover.jpg",
        "title": "律師官網",
        "date": "2022",
        "id": "web3"
    },
    {
        "img": "cover/bniWebCover.jpg",
        "title": "BNI官網",
        "date": "2022",
        "id":"web4"
    },
    {
        "img": "cover/DosportWebCover.jpg",
        "title": "搞運彩",
        "date": "2022",
        "id": "web5"
    }
    
    
]